aiter_timeouts-1.1.0.dist-info/METADATA
aiter_timeouts-1.1.0.dist-info/WHEEL
aiter_timeouts-1.1.0.dist-info/licenses/LICENSE
aiter_timeouts/__init__.py
aiter_timeouts-1.1.0.dist-info/RECORD
