Metadata-Version: 2.1
Name: aiter-timeouts
Version: 1.1.0
Summary: Timeout functionality for asynchronous iterators
Author-Email: Elias Gabriel <me@eliasfgabriel.com>
License: MIT
Project-URL: Documentation, https://github.com/thearchitector/aiter-timeouts
Project-URL: Repository, https://github.com/thearchitector/aiter-timeouts
Project-URL: Changelog, https://github.com/thearchitector/aiter-timeouts/blob/main/CHANGELOG.md
Requires-Python: >=3.7
